xviz_avs/__init__.py
xviz_avs/_version.py
xviz_avs/message.py
xviz_avs/builder/__init__.py
xviz_avs/builder/base_builder.py
xviz_avs/builder/future_instance.py
xviz_avs/builder/link.py
xviz_avs/builder/metadata.py
xviz_avs/builder/pose.py
xviz_avs/builder/primitive.py
xviz_avs/builder/time_series.py
xviz_avs/builder/ui_primitive.py
xviz_avs/builder/variable.py
xviz_avs/builder/xviz_builder.py
xviz_avs/builder/xviz_ui_builder.py
xviz_avs/builder/declarative_ui/__init__.py
xviz_avs/builder/declarative_ui/base_ui_builder.py
xviz_avs/builder/declarative_ui/base_ui_component.py
xviz_avs/builder/declarative_ui/constants.py
xviz_avs/builder/declarative_ui/container.py
xviz_avs/builder/declarative_ui/metric.py
xviz_avs/builder/declarative_ui/panel.py
xviz_avs/builder/declarative_ui/plot.py
xviz_avs/builder/declarative_ui/select.py
xviz_avs/builder/declarative_ui/table.py
xviz_avs/builder/declarative_ui/treetable.py
xviz_avs/builder/declarative_ui/video.py
xviz_avs/io/__init__.py
xviz_avs/io/base.py
xviz_avs/io/gltf.py
xviz_avs/io/json.py
xviz_avs/io/protobuf.py
xviz_avs/io/sources.py
xviz_avs/server/__init__.py
xviz_avs/server/handlers.py
xviz_avs/server/server.py
xviz_avs/server/sessions.py
xviz_avs/v2/__init__.py
xviz_avs/v2/annotation_pb2.py
xviz_avs/v2/core_pb2.py
xviz_avs/v2/envelope_pb2.py
xviz_avs/v2/options_pb2.py
xviz_avs/v2/primitives_pb2.py
xviz_avs/v2/session_pb2.py
xviz_avs/v2/style_pb2.py
xviz_avs/v2/uiprimitives_pb2.py
xviz_avs-0.1.0a5.dist-info/LICENSE
xviz_avs-0.1.0a5.dist-info/METADATA
xviz_avs-0.1.0a5.dist-info/WHEEL
xviz_avs-0.1.0a5.dist-info/top_level.txt
xviz_avs-0.1.0a5.dist-info/RECORD
