Metadata-Version: 2.1
Name: xviz-avs
Version: 0.1.0a5
Summary: Python implementation of XVIZ protocol
Home-page: https://github.com/uber/xviz
Author: Timothy Wojtaszek
Author-email: twojtasz@uber.com
License: UNKNOWN
Platform: UNKNOWN
Classifier: Programming Language :: Python :: 3
Classifier: Operating System :: OS Independent
Classifier: Development Status :: 2 - Pre-Alpha
Classifier: Topic :: Scientific/Engineering :: Visualization
Classifier: Topic :: Database :: Front-Ends
Classifier: Environment :: Web Environment
Requires-Dist: easydict
Requires-Dist: numpy
Requires-Dist: protobuf
Requires-Dist: websockets
